pynindo/__init__.py
pynindo/__main__.py
pynindo/cli.py
pynindo/const.py
pynindo/nindo.py
pynindo-0.1.2.dist-info/METADATA
pynindo-0.1.2.dist-info/WHEEL
pynindo-0.1.2.dist-info/entry_points.txt
pynindo-0.1.2.dist-info/top_level.txt
pynindo-0.1.2.dist-info/RECORD
