Metadata-Version: 2.1
Name: pynindo
Version: 0.1.2
Summary: The Python API for Nindo.de
Home-page: https://github.com/axju/pynindo
Author: axju
Author-email: axel.juraske@short-report.de
License: MIT
Platform: UNKNOWN
Classifier: Intended Audience :: Developers
Classifier: Operating System :: OS Independent
Classifier: Programming Language :: Python
Classifier: Programming Language :: Python :: 3.5
Classifier: Programming Language :: Python :: 3.6
Classifier: Programming Language :: Python :: 3.7
Classifier: Programming Language :: Python :: 3.8
Requires-Dist: requests
